horama/__init__.py
horama/common.py
horama/feature_accentuation.py
horama/fourier_fv.py
horama/losses.py
horama/maco_fv.py
horama/plots.py
horama-0.3.0.dist-info/licenses/LICENSE
tests/__init__.py
tests/common.py
tests/test_fa.py
tests/test_fourier.py
tests/test_maco.py
tests/test_plots.py
tests/test_timm.py
horama-0.3.0.dist-info/METADATA
horama-0.3.0.dist-info/WHEEL
horama-0.3.0.dist-info/top_level.txt
horama-0.3.0.dist-info/RECORD
