Metadata-Version: 2.4
Name: Horama
Version: 0.3.0
Summary: Personal toolbox for experimenting with Feature Visualization
Author: Thomas FEL, Thibaut BOISSIN, Victor BOUTIN, Agustin PICARD, Paul NOVELLO
Author-email: thomas_fel@brown.edu
License: MIT
Classifier: Development Status :: 4 - Beta
Classifier: License :: OSI Approved :: MIT License
Classifier: Programming Language :: Python
Classifier: Programming Language :: Python :: 3
Classifier: Operating System :: OS Independent
Requires-Python: >=3.6
License-File: LICENSE
Requires-Dist: numpy
Requires-Dist: matplotlib
Requires-Dist: torch
Requires-Dist: torchvision
Dynamic: author
Dynamic: author-email
Dynamic: classifier
Dynamic: description
Dynamic: description-content-type
Dynamic: license
Dynamic: license-file
Dynamic: requires-dist
Dynamic: requires-python
Dynamic: summary
